{
  "VERY": {
    "Definition": "exact, specific"
  },
  "SYNONYMOUS": {
    "Definition": "having the same meaning"
  },
  "UNSCRUPULOUS": {
    "Definition": "not honest or fair"
  },
  "SCHEMING": {
    "Definition": "making plans in order to do something illegal or wrong"
  },
  "CUNNING": {
    "Definition": "clever or skillful at getting what they want, especially by tricking or fooling people"
  },
  "TREACHERY": {
    "Definition": "behaviour that is not loyal, an act of treason"
  },
  "DECEPTION": {
    "Definition": "the act of causing someone to believe something that is not true, especially for personal gain"
  },
  "UPHEAVAL": {
    "Definition": "violent or sudden change"
  },
  "INTRIGUE": {
    "Definition": "secret plans or plots"
  },
  "TUMULTUOUS": {
    "Definition": "characterised by disagreement, disorder or confusion, turbulent"
  },
  "AGITATED": {
    "Definition": "angry or troubled"
  },
  "TURBULENT": {
    "Definition": "characterised by disagreement, disorder or confusion"
  },
  "SHAPE": {
    "Definition": "have great effect on"
  },
  "EPICENTRE": {
    "Definition": "central point"
  },
  "TRANSITIONAL": {
    "Definition": "relating to a change from one period to another"
  },
  "REVIVED": {
    "Definition": "brought back into existence"
  },
  "SURPASS": {
    "Definition": "do better than"
  },
  "FERVENT": {
    "Definition": "intense, passionate"
  },
  "FRAGMENTED": {
    "Definition": "consisting of separate parts"
  },
  "SPLIT UP": {
    "Definition": "separated, divided"
  },
  "INFLUENTIAL": {
    "Definition": "having a lot of influence or effect"
  },
  "WAGE WARS": {
    "Definition": "start or engage in wars"
  },
  "SHORT-LIVED": {
    "Definition": "lasting only for a short time"
  },
  "MERCENARY": {
    "Definition": "paid soldier"
  },
  "WERE PRONE TO": {
    "Definition": "were likely to"
  },
  "BACKDROP": {
    "Definition": "setting, environment"
  },
  "INSTABILITY": {
    "Definition": "a situation characterised by sudden changes and uncertainty"
  },
  "MANOEUVRING": {
    "Definition": "careful planning in order to get advantages"
  },
  "DISTINCT": {
    "Definition": "clearly different or noticeable"
  },
  "CRYSTALISED": {
    "Definition": "formed, made definite and clear"
  },
  "RHETORIC": {
    "Definition": "the art of effective speaking or writing"
  },
  "ARDENT": {
    "Definition": "showing strong feelings, enthusiastic"
  },
  "PATRON": {
    "Definition": "supporter"
  },
  "EXILED": {
    "Definition": "sent away from his country for political reasons"
  },
  "SHAPED": {
    "Definition": "formed"
  },
  "APPOINTED": {
    "Definition": "officially chosen for"
  },
  "ILLEGITIMATE": {
    "Definition": "born of parents not married to each other"
  },
  "CARVE OUT": {
    "Definition": "create, establish"
  },
  "RUTHLESS": {
    "Definition": "showing no compassion or pity, cruel"
  },
  "QUEST": {
    "Definition": "the act of looking for it and having it as a goal"
  },
  "IMMENSE": {
    "Definition": "extremely great in degree or level"
  },
  "RETAIN": {
    "Definition": "keep, continue to have"
  },
  "ALLIED": {
    "Definition": "connected by a political or military agreement"
  },
  "INTENT": {
    "Definition": "goal, aim"
  },
  "CRUSHING": {
    "Definition": "destroying"
  },
  "FRICTION": {
    "Definition": "disagreement, conflict"
  },
  "MERCENARIES": {
    "Definition": "paid soldiers"
  },
  "DELICATE": {
    "Definition": "easily damaged, fragile"
  },
  "COMPLY": {
    "Definition": "act according to, obey"
  },
  "THUS": {
    "Definition": "in this way"
  },
  "SACKED": {
    "Definition": "dismissed, discharged"
  },
  "CONSPIRED": {
    "Definition": "made secret plans"
  },
  "PLOTTED": {
    "Definition": "made secret plans"
  },
  "OVERTHROW": {
    "Definition": "remove from power"
  },
  "RETREAT": {
    "Definition": "move out, withdraw"
  },
  "RURAL": {
    "Definition": "located in the countryside"
  },
  "PENNED": {
    "Definition": "wrote"
  },
  "CONTEMPORARIES": {
    "Definition": "people of his time"
  },
  "STRUGGLED": {
    "Definition": "found it difficult"
  },
  "CORRESPONDENCE": {
    "Definition": "letters"
  },
  "SPHERE": {
    "Definition": "area of field of activity"
  },
  "OF SORTS": {
    "Definition": "to some extent, in some way"
  },
  "COMMISSIONED": {
    "Definition": "formally asked"
  },
  "GETTING BACK INTO THE GOOD BOOKS": {
    "Definition": "being accepted or approved again by"
  },
  "PORTRAYS": {
    "Definition": "represents, describes"
  },
  "TURN OUT": {
    "Definition": "prove, be in the end"
  },
  "KICKED OUT": {
    "Definition": "forced to leave, thrown out"
  },
  "RUSHED": {
    "Definition": "dealt with it quickly, in a hurry"
  },
  "NORM": {
    "Definition": "usual, standard thing"
  },
  "CONDUCT": {
    "Definition": "manner or way in which they behave"
  },
  "PRINCIPLES": {
    "Definition": "basic ideas"
  },
  "PRINCELY": {
    "Definition": "related to princes"
  },
  "IN TURN": {
    "Definition": "afterwards, subsequently"
  },
  "PAVED THE WAY": {
    "Definition": "opened the way"
  },
  "HEREDITARY": {
    "Definition": "having the title as a right passed by his parents"
  },
  "UPSETTING": {
    "Definition": "disorganising, disturbing"
  },
  "SCHEME": {
    "Definition": "organisation, particular system"
  },
  "CEMENT": {
    "Definition": "secure"
  },
  "TOPPLE": {
    "Definition": "cause them to lose power, bring down"
  },
  "BRING DOWN": {
    "Definition": "cause them to lose power"
  },
  "CRUSHED": {
    "Definition": "defeated"
  },
  "SELF-SUFFICIENT": {
    "Definition": "able to support himself, independent"
  },
  "SETTING OUT": {
    "Definition": "presenting, describing"
  },
  "CHARACTER TRAITS": {
    "Definition": "character qualities or characteristics"
  },
  "CONSOLIDATE": {
    "Definition": "cause it to be greater"
  },
  "DEVOID OF": {
    "Definition": "separate from"
  },
  "UNSCRUPULOUSLY": {
    "Definition": "in a dishonest or unfair way"
  },
  "FRAUD": {
    "Definition": "cheating or tricking people for personal gain"
  },
  "DECEIT": {
    "Definition": "the act of causing someone to believe something that is not true, especially for personal gain"
  },
  "DRAWS UPON": {
    "Definition": "makes use of"
  },
  "NOTABLY": {
    "Definition": "in particular, especially"
  },
  "BEING DRIVEN OUT": {
    "Definition": "being forced to leave"
  },
  "STATECRAFT": {
    "Definition": "management of state affairs or the art of governing and politics"
  },
  "BE DRIVEN OUT": {
    "Definition": "be forced to leave"
  },
  "SINGLING OUT": {
    "Definition": "giving special attention to"
  },
  "PINPOINTING": {
    "Definition": "finding and showing exactly"
  },
  "DOWNFALL": {
    "Definition": "loss of power and status"
  },
  "DOWNFALLS": {
    "Definition": "losses of power and status"
  },
  "FIRST-HAND": {
    "Definition": "coming from personal experience"
  },
  "PORTRAYED": {
    "Definition": "presented, described"
  },
  "CARVING OUT": {
    "Definition": "creating, establishing"
  },
  "IN LINE WITH": {
    "Definition": "in accordance or agreement with"
  },
  "FUNDAMENTAL": {
    "Definition": "basic, of central importance"
  },
  "EVENTUALITIES": {
    "Definition": "possible events"
  },
  "BROUGHT DOWN": {
    "Definition": "caused to lose power"
  },
  "INCAPACITATED": {
    "Definition": "disabled, ill"
  },
  "CURVEBALL": {
    "Definition": "something unexpected that causes trouble"
  },
  "ASPIRING": {
    "Definition": "someone who is trying to become successful"
  },
  "FAMED": {
    "Definition": "well known or famous"
  },
  "BYWORD": {
    "Definition": "expression"
  },
  "VERNACULAR": {
    "Definition": "common"
  },
  "REGAIN": {
    "Definition": "take back"
  },
  "TREATISE": {
    "Definition": "a formal piece of writing"
  },
  "SUPPORTED": {
    "Definition": "suggested or proved"
  },
  "DEVILED": {
    "Definition": "considered as bad or immoral"
  },
  "SHOCKINGLY": {
    "Definition": "in a way that is very unpleasant, offensive or disturbing"
  },
  "EMANCIPATED": {
    "Definition": "separated, made it independant"
  },
  "DETACHED": {
    "Definition": "separated"
  },
  "STRIKES A CHORD": {
    "Definition": "causes strong emotions"
  },
  "CALL TO ACTION": {
    "Definition": "something that asks or encourages people to take action"
  },
  "ADVICE": {
    "Definition": "recommendations, suggestions or guidance"
  },
  "BOLD": {
    "Definition": "not afraid of danger, risky"
  },
  "BRAZEN": {
    "Definition": "forward, without shame"
  },
  "SHAMELESS": {
    "Definition": "having no sense of shame or regrets for behaving in a way that is unacceptable for some people"
  },
  "HOLD ON": {
    "Definition": "keep, retain"
  },
  "STRIKE": {
    "Definition": "impress, affect"
  },
  "MATTER OF FACT": {
    "Definition": "not showing feelings or emotion"
  },
  "DECORUM": {
    "Definition": "controlled, calm, polite behaviour"
  },
  "INHERENTLY": {
    "Definition": "in a permanent or characteristic way"
  },
  "UNDERHAND": {
    "Definition": "secret, not honest"
  },
  "WORRYINGLY": {
    "Definition": "in a way that causes worry or concern"
  },
  "EXPOSES": {
    "Definition": "makes visible, reveals"
  },
  "AT ALL COSTS": {
    "Definition": "regardless of the price to be paid or the effort needed"
  },
  "SUGGESTING": {
    "Definition": "proposing, recommending"
  },
  "ENGAGED IN": {
    "Definition": "was involved in"
  },
  "ABSTRACT": {
    "Definition": "existing only in thought or as an idea"
  },
  "ATROCITIES": {
    "Definition": "extremely cruel or shocking acts"
  },
  "RESORT TO": {
    "Definition": "turn to, make use of (usually as a final option)"
  },
  "DECEITFULNESS": {
    "Definition": "acts of causing people to believe something that is not true, especially for personal gain"
  },
  "WHEN PUSH COMES TO SHOVE": {
    "Definition": "when the situation is very serious or urgent"
  },
  "GO TO EXTRAORDINARY LENGTHS": {
    "Definition": "use a lot of effort, do whatever is required"
  },
  "": {
    "Definition": null
  }
}