{
  "ACCESSIBILITY": {
    "Defintion": "ease of use, ease to get"
  },
  "AIDE": {
    "Defintion": "an important assistant"
  },
  "BEHIND BARS": {
    "Defintion": "in prison"
  },
  "BINGO": {
    "Defintion": "(colloquial) there you go"
  },
  "CATALOGUE": {
    "Defintion": "a magazine with a list of things you can buy"
  },
  "CLAMPING DOWN": {
    "Defintion": "to take action against something"
  },
  "COUNTER ARGUMENT": {
    "Defintion": "a point that is opposite to what was previously said"
  },
  "CRACKDOWN": {
    "Defintion": "see 'cracking down'"
  },
  "CRACKING DOWN": {
    "Defintion": "dealing with severely"
  },
  "DECLARATION": {
    "Defintion": "an official announcement"
  },
  "DECRIMINALISING": {
    "Defintion": "stopping something from being illegal"
  },
  "DECRIMINALIZED": {
    "Defintion": "stopped from being illegal"
  },
  "DETRIMENT": {
    "Defintion": "harm, negative effect"
  },
  "DEVASTATING": {
    "Defintion": "very bad, causing a lot of damage"
  },
  "DRUG REHABILITATION": {
    "Defintion": "helping drug addicts stop using drugs"
  },
  "ELIMINATE": {
    "Defintion": "get rid of completely"
  },
  "ERADICATE": {
    "Defintion": "get rid of completely"
  },
  "EVERY MAN AND HIS DOG": {
    "Defintion": "(colloquial) everyone"
  },
  "GATEWAY DRUGS": {
    "Defintion": "drugs that make it more likely that a harder (and more dangerous) drug will be used"
  },
  "HABITS": {
    "Defintion": "(of drugs) addiction"
  },
  "HIPPIE": {
    "Defintion": "someone in the 1960s and 1970s who was against violence"
  },
  "HIPPY": {
    "Defintion": "someone in the 1960s and 1970s who was against violence"
  },
  "ICONIC": {
    "Defintion": "very famous or well known"
  },
  "IMPLICIT": {
    "Defintion": "suggested or understood, but not said"
  },
  "INCARCERATED": {
    "Defintion": "put in prison"
  },
  "INCARCERATION": {
    "Defintion": "imprisonment"
  },
  "INORDINATE": {
    "Defintion": "much more than expected or would be fair"
  },
  "INSOMNIA": {
    "Defintion": "the condition of not being able to sleep"
  },
  "ISOLATED": {
    "Defintion": "obtained or extracted"
  },
  "LIBERTARIAN": {
    "Defintion": "someone who thinks that people should be free to do what they please without government interference"
  },
  "LOFTY": {
    "Defintion": "high"
  },
  "LUCRATIVE": {
    "Defintion": "produces a lot of money"
  },
  "MENACE": {
    "Defintion": "threat, something that is likely to cause harm"
  },
  "MORPHINE": {
    "Defintion": "a drug made from opium, often used for pain relief"
  },
  "NIGH": {
    "Defintion": "or even"
  },
  "OPIATES": {
    "Defintion": "drugs that contain opium, often used for pain relief"
  },
  "OPIUM": {
    "Defintion": "a drug made from poppy seeds"
  },
  "PANEL": {
    "Defintion": "a small group"
  },
  "POLICYMAKERS": {
    "Defintion": "people who decide policy and laws"
  },
  "PROHIBITION": {
    "Defintion": "officially not allowing something"
  },
  "PROPHECIES": {
    "Defintion": "statements about what will happen in the future"
  },
  "RAID": {
    "Defintion": "make a surprise visit (especially by police or soldiers)"
  },
  "RAW MATERIALS": {
    "Defintion": "the base ingredients"
  },
  "RECREATIONAL": {
    "Defintion": "(of drugs) non-medical"
  },
  "SHOUT OUTS": {
    "Defintion": "(colloquial) public congratulations"
  },
  "SKYROCKET": {
    "Defintion": "Increase quickly"
  },
  "SOMETHING HAS TO GIVE": {
    "Defintion": "you can't have everything"
  },
  "SYNTHESISED": {
    "Defintion": "produce a substance via a chemical reaction"
  },
  "SYRINGE": {
    "Defintion": "a medical piece of equipment used for sucking liquid out or inserting liquid into somewhere"
  },
  "SYRINGES": {
    "Defintion": "a medical piece of equipment used for sucking liquid out or inserting liquid into somewhere"
  },
  "TABOOS": {
    "Defintion": "subjects that are avoided"
  },
  "TOLERATED": {
    "Defintion": "accepted, allowed"
  },
  "TRAUMA": {
    "Defintion": "severe shock"
  },
  "URGENT": {
    "Defintion": "very important and requiring action"
  },
  "VAST MAJORITY": {
    "Defintion": "almost all"
  },
  "VEINS": {
    "Defintion": "the tubes that carry blood to the heart"
  },
  "VETERANS": {
    "Defintion": "soldiers who fought in a war"
  },
  "VILIFY": {
    "Defintion": "to talk about in a negative way in order to get others to develop a negative opinion (of that person or group)"
  },
  "WAGED": {
    "Defintion": "start (a war)"
  }
}